= String, StringBuilder, StringBuffer
:listing-caption!:

* [x] String, StringBuilder, StringBuffer 란 무엇인가?

== String 클래스
일반적으로 `String` 을 `new` 연산자로 생성하지 않고 기본형 변수처럼 `=` 를 사용해서 생성하지만, 엄연히 참조형 변수이다. String 객체가 생성될 때 내부적으로 문자형 배열(char[])을 사용해서 문자열을 입력받게 된다.

[source,java]
----
public final class String
    implements java.io.Serializable, Comparable<String>, CharSequence {
    /** The value is used for character storage. */
    private final char value[];
    ...
}
----

=== 불변 객체
`char[]` 배열의 `final` 을 보면 알 수 있듯이, `String` 객체는 불변이다. 즉, 한번 생성하면 변경할 수 없단 얘기다. `String` 문자열을 다른 것과 합치게 되면, 합쳐진 새로운 `String` 객체가 생성되고, 참조를 잃은 이전 객체는 GC의 대상이 된다.

.StringTest.java
[#StringTest,java]
----
public class StringTest {
    public static void main(String[] args) {
        String a = "Adventure";
        a += "Time";

        String b = "Adventure";
        String c = "Adventure";
    }
}
----

image::1.png[]

=== 문자 리터럴
자바 소스파일에 포함된 모든 문자열 리터럴은 컴파일 시에 클래스 파일의 런타임 상수 풀에 저장되는데, 이때 문자 리터럴은 한번만 저장되어 공유된다.
xref:StringTest[위 소스]에서 보면 `Adventrue` 라는 문자열을 여러 번 생성했지만 상수풀에는 #28 에 한번만 저장되어 있고, 바이트코드에서 봐도 동일한 상수풀 주소(#2)을 참조하고 있다.
[source,]
----
Constant pool:
   #1 = Methodref          #9.#27         // java/lang/Object."<init>":()V
   #2 = String             #28            // Adventure
   #3 = Class              #29            // java/lang/StringBuilder
   #4 = Methodref          #3.#27         // java/lang/StringBuilder."<init>":()V
   #5 = Methodref          #3.#30         // java/lang/StringBuilder.append:(Ljava/lang/String;)Ljava/lang/StringBuilder;
   #6 = String             #31            // Time
   #7 = Methodref          #3.#32         // java/lang/StringBuilder.toString:()Ljava/lang/String;
   #8 = Class              #33            // org/example/StringTest
   #9 = Class              #34            // java/lang/Object
  #10 = Utf8               <init>
  #11 = Utf8               ()V
  #12 = Utf8               Code
  #13 = Utf8               LineNumberTable
  #14 = Utf8               LocalVariableTable
  #15 = Utf8               this
  #16 = Utf8               Lorg/example/StringTest;
  #17 = Utf8               main
  #18 = Utf8               ([Ljava/lang/String;)V
  #19 = Utf8               args
  #20 = Utf8               [Ljava/lang/String;
  #21 = Utf8               a
  #22 = Utf8               Ljava/lang/String;
  #23 = Utf8               b
  #24 = Utf8               c
  #25 = Utf8               SourceFile
  #26 = Utf8               StringTest.java
  #27 = NameAndType        #10:#11        // "<init>":()V
  #28 = Utf8               Adventure <.>
  #29 = Utf8               java/lang/StringBuilder
  #30 = NameAndType        #35:#36        // append:(Ljava/lang/String;)Ljava/lang/StringBuilder;
  #31 = Utf8               Time
  #32 = NameAndType        #37:#38        // toString:()Ljava/lang/String;
  #33 = Utf8               org/example/StringTest
  #34 = Utf8               java/lang/Object
  #35 = Utf8               append
  #36 = Utf8               (Ljava/lang/String;)Ljava/lang/StringBuilder;
  #37 = Utf8               toString
  #38 = Utf8               ()Ljava/lang/String;

 0: ldc           #2                  // String Adventure
 2: astore_1
 3: new           #3                  // class java/lang/StringBuilder
 6: dup
 7: invokespecial #4                  // Method java/lang/StringBuilder."<init>":()V
10: aload_1
11: invokevirtual #5                  // Method java/lang/StringBuilder.append:(Ljava/lang/String;)Ljava/lang/StringBuilder;
14: ldc           #6                  // String Time
16: invokevirtual #5                  // Method java/lang/StringBuilder.append:(Ljava/lang/String;)Ljava/lang/StringBuilder;
19: invokevirtual #7                  // Method java/lang/StringBuilder.toString:()Ljava/lang/String;
22: astore_1
23: ldc           #2                  // String Adventure <.>
25: astore_2
26: ldc           #2                  // String Adventure
28: astore_3
29: return
----

=== 생성자 사용
위에서 본 것 처럼 문자열 리터럴을 지정하는 것이 아닌, `new` 연산자를 사용하여 문자열을 생성할 수 있는데, 이 때는 같은 문자열이라고 할지라도 새로운 메모리를 할당받고 새로운 String 객체를 생성하게 된다. 문자열 리터럴은 이미 존재하면 재사용이 가능하지만 생성자를 통해 만들게 되면 매번 새로운 객체를 만드는 것이다.